{
  "commits" : [
    {
      "name" : "glslang",
      "site" : "github",
      "subrepo" : "KhronosGroup/glslang",
      "subdir" : "third_party/glslang",
      "commit" : "142052fa30f9eca191aa9dcf65359fcaed09eeec"
    },
    {
      "name" : "abseil_cpp",
      "site" : "github",
      "subrepo" : "abseil/abseil-cpp",
      "subdir" : "third_party/abseil_cpp",
      "commit" : "5be22f98733c674d532598454ae729253bc53e82"
    },
    {
      "name" : "re2",
      "site" : "github",
      "subrepo" : "google/re2",
      "subdir" : "third_party/re2",
      "commit" : "c9cba76063cf4235c1a15dd14a24a4ef8d623761"
    },
    {
      "name" : "effcee",
      "site" : "github",
      "subrepo" : "google/effcee",
      "subdir" : "third_party/effcee",
      "commit" : "aea1f4d62ca9ee2f44b5393e98e175e200a22e8e"
    },
    {
      "name" : "googletest",
      "site" : "github",
      "subrepo" : "google/googletest",
      "subdir" : "third_party/googletest",
      "commit" : "e47544ad31cb3ceecd04cc13e8fe556f8df9fe0b"
    },
    {
      "name" : "shaderc",
      "site" : "github",
      "subrepo" : "google/shaderc",
      "commit" : "47a9387ef5b3600d30d84c71ec77a59dc7db46fa"
    },
    {
      "name" : "spirv-headers",
      "site" : "github",
      "subrepo" : "KhronosGroup/SPIRV-Headers",
      "subdir" : "third_party/spirv-tools/external/spirv-headers",
      "commit" : "5e3ad389ee56fca27c9705d093ae5387ce404df4"
    },
    {
      "name" : "spirv-tools",
      "site" : "github",
      "subrepo" : "KhronosGroup/SPIRV-Tools",
      "subdir" : "third_party/spirv-tools",
      "commit" : "dd4b663e13c07fea4fbb3f70c1c91c86731099f7"
    }
  ]
}
